lstm_model/VERSION
lstm_model/__init__.py
lstm_model/config.yml
lstm_model/lstm_pipeline.py
lstm_model/pipeline.py
lstm_model/predict.py
lstm_model/config/__init__.py
lstm_model/config/core.py
lstm_model/datasets/EURUSD_Candlestick_1_h_ASK_31.12.2011-31.01.2023.csv
lstm_model/datasets/__init__.py
lstm_model/processing/__init__.py
lstm_model/processing/data_manager.py
lstm_model/processing/pipe_needs.py
lstm_model/trained_models/LSTM_pipe_saved1.0.0.pkl
lstm_model/trained_models/__init__.py
basic_lstm_model-1.0.0.dist-info/METADATA
basic_lstm_model-1.0.0.dist-info/WHEEL
basic_lstm_model-1.0.0.dist-info/top_level.txt
basic_lstm_model-1.0.0.dist-info/RECORD
